rtl/MAC/MAC.v
module MAC
    (
        input wire [15:0] x,
        input wire [15:0] coeff,
        input wire clk,
        input wire rst,
        output reg [31:0] y,
        output reg tick
    );

reg signed [31:0] accum;
reg [15:0] X;
reg [15:0] COEFF;
reg [5:0] counter;


always @ (posedge clk)
    begin
	if(rst)
	    begin
            	accum = 32'b0;
            	X = 16'b0;
            	COEFF = 16'b0;
            	counter = 6'b0;
		y <= 32'b0;
		tick <= 1'b0;
	    end
	
	else begin
        tick <= 1'b0;
        X = x;
        COEFF = coeff;
        accum = accum + ($signed(X) * $signed(COEFF));
        counter = counter + 1'b1;

        if(counter == 6'b0)
            begin
                counter = 6'b0;
                y <= accum;
                tick <= 1'b1;
		accum = 32'b0;
            end
	end

    end

endmodule

qsim_rtl/MAC/MAC_TB.v
`timescale 1ns/1ps
`define SD #0.010
`define HALF_CLOCK_PERIOD #5
`define QSIM_OUT_FN "./qsim.out"

module MAC_TB();

reg clk;
reg reset;

reg [15:0] xVals [0:63];
reg [15:0] currX;
reg [15:0] coeffVals [0:63];
reg [15:0] currCoeff;
reg [5:0]  address;
wire [31:0] y;
wire mac_tick;

MAC uut0 (.x(currX), .coeff(currCoeff), .clk(clk), .rst(reset), .y(y), .tick(mac_tick));


initial
    begin
        currX = 16'b0;
        currCoeff = 16'b0;
	address = 6'b0;
	$readmemb("xVals.txt", xVals);
	$readmemb("coeffVals.txt", coeffVals);
	$dumpfile("./MAC.vcd");
        $dumpvars(0,MAC_TB.uut0);
        reset = 1'b1;
        #16;
        reset = 1'b0;	
    end


always
    begin
	clk = 1'b1;
	#5;
	clk = 1'b0;
	#5;
    end

always @ (negedge clk)
    begin
        if(mac_tick)begin
	    $dumpall;
            $dumpflush;
            $finish;
	end
	if (~reset) begin
	    if ( address < 63 ) begin
		address <= address + 1;
	    end
	end

    end

always @ (address)
    begin
	currX = xVals[address];
	currCoeff = coeffVals[address];
    end


endmodule

qsim_rtl/MAC/MAC.vcd
$date
	Sun Nov 17 23:19:54 2024
$end
$version
	ModelSim Version 2024.2
$end
$timescale
	1ps
$end

$scope module MAC_TB $end

$scope module uut0 $end
$var wire 1 ! x [15] $end
$var wire 1 " x [14] $end
$var wire 1 # x [13] $end
$var wire 1 $ x [12] $end
$var wire 1 % x [11] $end
$var wire 1 & x [10] $end
$var wire 1 ' x [9] $end
$var wire 1 ( x [8] $end
$var wire 1 ) x [7] $end
$var wire 1 * x [6] $end
$var wire 1 + x [5] $end
$var wire 1 , x [4] $end
$var wire 1 - x [3] $end
$var wire 1 . x [2] $end
$var wire 1 / x [1] $end
$var wire 1 0 x [0] $end
$var wire 1 1 coeff [15] $end
$var wire 1 2 coeff [14] $end
$var wire 1 3 coeff [13] $end
$var wire 1 4 coeff [12] $end
$var wire 1 5 coeff [11] $end
$var wire 1 6 coeff [10] $end
$var wire 1 7 coeff [9] $end
$var wire 1 8 coeff [8] $end
$var wire 1 9 coeff [7] $end
$var wire 1 : coeff [6] $end
$var wire 1 ; coeff [5] $end
$var wire 1 < coeff [4] $end
$var wire 1 = coeff [3] $end
$var wire 1 > coeff [2] $end
$var wire 1 ? coeff [1] $end
$var wire 1 @ coeff [0] $end
$var wire 1 A clk $end
$var wire 1 B rst $end
$var reg 32 C y [31:0] $end
$var reg 1 D tick $end
$var reg 32 E accum [31:0] $end
$var reg 16 F X [15:0] $end
$var reg 16 G COEFF [15:0] $end
$var reg 6 H counter [5:0] $end
$upscope $end
$upscope $end
$enddefinitions $end
#0
$dumpvars
b0 C
0D
b0 E
b0 F
b0 G
b0 H
1B
1A
1@
1?
1>
1=
0<
0;
0:
19
18
17
16
15
14
13
12
11
10
0/
0.
0-
0,
1+
1*
1)
1(
1'
1&
1%
1$
0#
1"
1!
$end
#5000
0A
#10000
1A
#15000
0A
#16000
0B
#20000
1A
b1101111111100001 F
b1111111110001111 G
b11100010110110101111 E
b1 H
#25000
0A
0?
0=
1<
09
08
07
06
05
04
03
02
01
00
1/
0)
0&
0%
1#
0!
#30000
1A
b111001101100010 F
b10101 G
b101111010010010111001 E
b10 H
#35000
0A
0@
0>
1=
0<
1:
18
17
16
15
14
13
12
11
10
1%
0"
#40000
1A
b11101101100011 F
b1111111101001000 G
b11111111111011001111010110010001 E
b11 H
#45000
0A
1?
1<
0:
19
08
07
06
05
04
03
02
01
0/
0+
0'
0#
#50000
1A
b1100101000001 F
b10011010 G
b11111111111111000010011010101011 E
b100 H
#55000
0A
1>
0=
0<
1;
09
18
17
16
15
14
13
12
11
00
1,
1+
1)
1'
1&
0%
0$
1#
1!
#60000
1A
b1010011111110000 F
b1111111100100110 G
b10001110010010001001011 E
b101 H
#65000
0A
1@
0?
0>
1=
1<
1:
19
08
07
06
05
04
03
02
01
10
1/
1.
1-
0,
#70000
1A
b1010011111101111 F
b11111001 G
b11111111111100010111101111000010 E
b110 H
#75000
0A
1?
0<
0;
0:
00
1,
0+
0(
1%
0#
#80000
1A
b1000111011011110 F
b10001011 G
b11111111101101000000111001001100 E
b111 H
#85000
0A
0?
1>
0=
1;
1:
09
18
17
16
15
14
13
12
11
10
0/
1+
0*
1(
0'
1$
1"
0!
#90000
1A
b101110110111101 F
b1111111101100101 G
b11111111011110110100110011011101 E
b1000 H
#95000
0A
0@
1?
0>
0;
0:
00
1/
0.
0-
0,
1*
0&
0"
#100000
1A
b1100111100010 F
b1111111100000010 G
b11111111011000011001111010100001 E
b1001 H
#105000
0A
1@
0?
1;
19
08
07
06
05
04
03
02
01
0/
1.
0+
0)
1&
0%
1#
#110000
1A
b11010101000100 F
b10100001 G
b11111111100000110001111001100101 E
b1010 H
#115000
0A
1=
1:
09
10
0$
0#
1!
#120000
1A
b1000010101000101 F
b1101001 G
b11111111010100001100011110110010 E
b1011 H
#125000
0A
1>
0=
1<
00
1-
0(
0&
1%
1$
1#
1"
0!
#130000
1A
b111100001001100 F
b1110101 G
b11111111100001111100001001101110 E
b1100 H
#135000
0A
0@
1?
0>
1=
0<
0;
0:
19
1/
0.
1,
0*
1(
1&
0%
0#
#140000
1A
b101010100011010 F
b10001010 G
b11111111101101011010001001110010 E
b1101 H
#145000
0A
1@
0?
1>
0=
1;
09
18
17
16
15
14
13
12
11
10
1*
0(
1'
1#
0"
1!
#150000
1A
b1011011001011011 F
b1111111100100101 G
b11111111111101001010001010011001 E
b1110 H
#155000
0A
1?
1<
19
00
0/
1.
0,
0*
1)
1%
0$
#160000
1A
b1010111010001100 F
b1111111110110111 G
b10111101110010101101 E
b1111 H
#165000
0A
0>
1=
09
10
1/
0.
0-
1,
1+
1*
#170000
1A
b1010111011110011 F
b1111111100111011 G
b10010100011101110101110 E
b10000 H
#175000
0A
0?
19
08
07
06
05
04
03
02
01
00
0,
1(
0'
0#
1"
#180000
1A
b1100110111100010 F
b10111001 G
b1001100000010000000000 E
b10001 H
#185000
0A
1?
1>
09
1.
1,
0+
0)
0(
1'
0%
0"
0!
#190000
1A
b11001010110 F
b111111 G
b1001111001001100101010 E
b10010 H
#195000
0A
0?
0>
0<
19
18
17
16
15
14
13
12
11
10
0.
0*
1)
1%
1#
1"
1!
#200000
1A
b1110111010010011 F
b1111111110101001 G
b1011010111111100110101 E
b10011 H
#205000
0A
0@
0=
09
0/
1.
1-
0,
0&
0#
#210000
1A
b1100101010001101 F
b1111111100100000 G
b10111000100001111010101 E
b10100 H
#215000
0A
1@
1?
1>
1=
1<
0;
19
00
1/
0.
0-
1+
0'
1&
1$
0"
0!
#220000
1A
b1110010100010 F
b1111111110011111 G
b10100010110101001110011 E
b10101 H
#225000
0A
0@
0=
0<
1;
10
0/
1.
1,
1(
1'
0&
0%
0$
1#
1!
#230000
1A
b1010001110110101 F
b1111111110100110 G
b11100011101110011010001 E
b10110 H
#235000
0A
1@
0?
1<
1:
09
08
07
06
05
04
03
02
01
0.
1-
0,
0+
1*
0(
1%
0#
1"
#240000
1A
b1100101011001001 F
b1110101 G
b10110011000101010101110 E
b10111 H
#245000
0A
0@
1?
0<
0;
1(
0'
1&
1$
#250000
1A
b1101110111001001 F
b1000110 G
b10100000010111110100100 E
b11000 H
#255000
0A
19
0-
0(
0%
1#
#260000
1A
b1111010011000001 F
b11000110 G
b10001110111110011101010 E
b11001 H
#265000
0A
1@
0?
0>
1<
1;
18
17
16
15
14
13
12
11
0*
0)
1(
0&
1%
0$
0#
0!
#270000
1A
b100100100000001 F
b1111111111110001 G
b10000110011010111011011 E
b11010 H
#275000
0A
1>
1=
0:
09
1.
1-
1,
1'
0%
1$
1#
0"
1!
#280000
1A
b1011001100011101 F
b1111111100111101 G
b11111011100011011000100 E
b11011 H
#285000
0A
0<
1:
08
07
06
05
04
03
02
01
00
0-
0,
1+
1)
0$
0#
0!
#290000
1A
b1110100100 F
b1101101 G
b11111110101001110011000 E
b11100 H
#295000
0A
0=
0;
0:
19
0.
1-
1&
1$
#300000
1A
b1011110101000 F
b10000101 G
b100010111001110111100000 E
b11101 H
#305000
0A
1?
1=
1<
09
1.
0-
1*
0&
1%
0$
1!
#310000
1A
b1000101111100100 F
b11111 G
b11111011000111001111100 E
b11110 H
#315000
0A
0@
0>
0<
19
0.
1-
0+
0*
1$
0!
#320000
1A
b1101110001000 F
b10001010 G
b100011000110010111001100 E
b11111 H
#325000
0A
0?
1>
1<
1;
1:
18
17
16
15
14
13
12
11
10
1/
1.
0-
1+
0$
1#
1!
#330000
1A
b1010101110100111 F
b1111111111111100 G
b100011011011011100110000 E
b100000 H
#335000
0A
1@
1?
0>
0<
0;
0:
09
08
07
06
05
04
03
02
01
0(
0'
0%
1$
0#
#340000
1A
b1001000010100111 F
b1011 G
b100010001110111001011101 E
b100001 H
#345000
0A
0@
1<
1:
19
18
17
16
15
14
13
12
11
00
0.
1-
1*
1'
1#
1"
0!
#350000
1A
b111001011101010 F
b1111111111011010 G
b11101111101111110100001 E
b100010 H
#355000
0A
1@
0?
1>
0<
0:
09
10
0-
1,
0*
0)
1(
1&
#360000
1A
b111011100110011 F
b1111111100001101 G
b1101011101000111000 E
b100011 H
#365000
0A
1?
0=
1<
1;
1*
1)
0(
1%
0$
0#
#370000
1A
b100111011110011 F
b1111111100110111 G
b11111111110010001011110101101101 E
b100100 H
#375000
0A
0@
0?
0>
0;
1-
1(
0'
1!
#380000
1A
b1100110111111011 F
b1111111100010000 G
b11111111111101111010001000011101 E
b100101 H
#385000
0A
1@
1>
0<
1:
08
07
06
05
04
03
02
01
0/
0-
0,
0+
0*
0)
0&
1$
0"
#390000
1A
b1001100100000001 F
b1000101 G
b11111111110110111101111101100010 E
b100110 H
#395000
0A
0@
0>
1;
0:
19
18
17
16
15
14
13
12
11
1-
1+
1'
1&
0$
1#
0!
#400000
1A
b10111100101001 F
b1111111110100000 G
b11111111110010100011000000000010 E
b100111 H
#405000
0A
1>
0;
09
08
07
06
05
04
03
02
01
1.
1)
0(
0'
0&
0%
1$
1"
1!
#410000
1A
b1111000010101101 F
b100 G
b11111111110010011111001010110110 E
b101000 H
#415000
0A
0>
1<
1:
19
1,
0)
1(
1'
1&
1%
0#
0"
#420000
1A
b1001111100111101 F
b11010000 G
b11111111011110110101010001000110 E
b101001 H
#425000
0A
1@
1?
1>
1=
1;
09
18
17
16
15
14
13
12
11
1/
0.
0-
0,
0+
1*
1)
0(
1#
1"
#430000
1A
b1111111011000011 F
b1111111101111111 G
b11111111011110111111010000000011 E
b101010 H
#435000
0A
0@
0>
0=
0;
19
0/
1.
1-
0'
0&
0$
0#
0"
#440000
1A
b1000100011001101 F
b1111111111010010 G
b11111111100100010101111100101101 E
b101011 H
#445000
0A
0<
0:
08
07
06
05
04
03
02
01
0.
1#
1"
0!
#450000
1A
b110100011001001 F
b10000010 G
b11111111110001101001010100111111 E
b101100 H
#455000
0A
1@
0?
1>
1<
1;
1:
09
18
17
16
15
14
13
12
11
1/
1.
1,
1+
0*
0)
1'
0%
0#
1!
#460000
1A
b1100001000111111 F
b1111111101110101 G
b11111111111010000001110100001010 E
b101101 H
#465000
0A
1?
0<
0:
0.
0+
1)
1(
0'
1%
1#
0"
0!
#470000
1A
b10100110011011 F
b1111111100100111 G
b11111111110001001101100010100111 E
b101110 H
#475000
0A
0@
0?
1<
0;
19
00
0/
1.
0,
1*
1'
1&
0#
1"
1!
#480000
1A
b1100111111001100 F
b1111111110010100 G
b11111111110110010010111010010111 E
b101111 H
#485000
0A
1?
0>
1:
09
10
1/
0.
0-
1+
0*
0)
0'
0%
0"
0!
#490000
1A
b10100100011 F
b1111111101010010 G
b11111111110101011011000011001101 E
b110000 H
#495000
0A
0?
1>
1=
19
08
07
06
05
04
03
02
01
0/
1.
1,
1*
1)
1'
0&
1%
#500000
1A
b101111110101 F
b11011100 G
b11111111110111111111011101011001 E
b110001 H
#505000
0A
1@
0:
00
1/
0.
0+
0)
1&
1#
1!
#510000
1A
b1010111101010010 F
b10011101 G
b11111111101011100111110010100011 E
b110010 H
#515000
0A
0@
0=
0<
1:
09
1.
1+
0*
0(
0'
0&
1$
1"
0!
#520000
1A
b111100000110110 F
b1000100 G
b11111111110011100110101011111011 E
b110011 H
#525000
0A
1?
1=
1<
1;
0:
19
10
1-
0,
1*
1'
1&
0%
0$
0#
#530000
1A
b100011001101111 F
b10111110 G
b101011000101011101 E
b110100 H
#535000
0A
1@
0>
0;
0.
0-
0+
0*
1)
0'
0&
1$
1#
#540000
1A
b111000010000011 F
b10011011 G
b10001101101000010101110 E
b110101 H
#545000
0A
1>
1:
09
18
17
16
15
14
13
12
11
1,
0)
1(
1&
0$
#550000
1A
b110010100010011 F
b1111111101011111 G
b1110011111110111011 E
b110110 H
#555000
0A
0@
0?
0>
0<
19
08
07
06
05
04
03
02
01
1.
1-
0,
0&
1%
1$
0#
0"
#560000
1A
b1100100001111 F
b11001000 G
b110101101001101110011 E
b110111 H
#565000
0A
1>
0=
1<
0:
09
1,
1+
1*
1)
1'
0$
1#
1"
#570000
1A
b110101111111111 F
b10100 G
b1000110100001101011111 E
b111000 H
#575000
0A
1@
1=
19
0-
0,
0*
0(
1&
0%
1$
0#
0"
1!
#580000
1A
b1001011010100111 F
b10011101 G
b11111111111000101010011111001010 E
b111001 H
#585000
0A
0@
1?
0>
0<
1:
0.
1-
0)
0&
1#
#590000
1A
b1011001000101011 F
b11001010 G
b11111111101001010011110110111000 E
b111010 H
#595000
0A
0=
1;
0:
18
17
16
15
14
13
12
11
00
0/
1.
0-
1,
0+
1)
1(
1%
0$
0#
#600000
1A
b1000101110010100 F
b1111111110100010 G
b11111111110011111111110101100000 E
b111011 H
#605000
0A
0?
1=
1<
09
0.
1-
0,
1*
0)
0%
1$
1"
#610000
1A
b1101001101001000 F
b1111111100111000 G
b11111111111100101110110100100000 E
b111100 H
#615000
0A
1>
0=
1:
0-
0*
1)
0$
1#
#620000
1A
b1110001110000000 F
b1111111101110100 G
b101000001100100000 E
b111101 H
#625000
0A
1?
0>
1=
0;
19
10
1/
1.
1,
1+
1*
0)
0'
1&
0#
#630000
1A
b1100010101110111 F
b1111111111011010 G
b10110011001101110110 E
b111110 H
#635000
0A
0=
0<
1;
0:
08
07
06
05
04
03
02
01
00
0/
0.
1-
0,
0*
0(
1$
0!
#640000
1A
b101010000101000 F
b10100010 G
b10000000111010011000110 E
b111111 H
#645000
0A
0?
1=
1<
1.
0-
1,
0+
1*
1(
1'
0&
1%
1!
#650000
1A
b1101101101010100 F
b10111000 G
b1001100001100100100110 E
b0 H
b0 E
b1001100001100100100110 C
1D
#655000
0A
$dumpall
b1001100001100100100110 C
1D
b0 E
b1101101101010100 F
b10111000 G
b0 H
0B
0A
0@
0?
0>
1=
1<
1;
0:
19
08
07
06
05
04
03
02
01
00
0/
1.
0-
1,
0+
1*
0)
1(
1'
0&
1%
1$
0#
1"
1!
$end
